{
  "usuarios": [
    {
      "id": "1",
      "nombre": "Juan Pérez",
      "correo": "juanperez@example.com",
      "contrasena": "hashedpassword1",
      "lugar_residencia": "San José",
      "numero_contacto": "+506 8888-9999"
    },
    {
      "id": "2",
      "nombre": "María Gómez",
      "correo": "mariagomez@example.com",
      "contrasena": "hashedpassword2",
      "lugar_residencia": "Cartago",
      "numero_contacto": "+506 7777-8888"
    },
    {
      "id": "3",
      "nombre": "Carlos Ramírez",
      "correo": "carlosramirez@example.com",
      "contrasena": "hashedpassword3",
      "lugar_residencia": "Alajuela",
      "numero_contacto": "+506 6666-7777"
    },
    {
      "id": "a419",
      "nombre": "Ana Fernández",
      "correo": "anafernandez@example.com",
      "contrasena": "hashedpassword4",
      "lugar_residencia": "Heredia",
      "numero_contacto": "+506 5555-6666"
    }
  ],
  "eventos": [
    {
      "id": "1",
      "categoria": "Ambiental",
      "nombre": "Reforestación en el parque",
      "descripcion": "Evento de reforestación para mejorar las áreas verdes.",
      "fecha": "2025-04-10",
      "lugar": "Parque Nacional",
      "voluntarios_requeridos": 20,
      "organizador_id": "1",
      "tareas": [
        {
          "nombre": "Repartir bolsas y guantes",
          "estado": "completado"
        },
        {
          "nombre": "Recolectar plásticos",
          "estado": "pendiente"
        },
        {
          "nombre": "Clasificar residuos",
          "estado": "pendiente"
        }
      ]
    },
    {
      "id": "2",
      "categoria": "Ambiental",
      "nombre": "Limpieza de Playa",
      "descripcion": "Actividad para recolectar desechos y limpiar la costa.",
      "fecha": "2025-04-20",
      "lugar": "Playa Tamarindo",
      "voluntarios_requeridos": 25,
      "organizador_id": "3",
      "tareas": [
        {
          "nombre": "Repartir bolsas y guantes",
          "estado": "pendiente"
        },
        {
          "nombre": "Recolectar plásticos",
          "estado": "pendiente"
        },
        {
          "nombre": "Clasificar residuos",
          "estado": "pendiente"
        }
      ]
    },
    {
      "id": "69c1",
      "title": "Limpieza de Playa",
      "date": "2025-04-20",
      "time": "09:00",
      "location": "Playa del Sol",
      "category": "Medio Ambiente",
      "description": "Un evento para limpiar la playa y crear conciencia ambiental.",
      "volunteersNeeded": 20,
      "requiredSkills": "Trabajo en equipo, limpieza",
      "optionalSkills": "Primeros auxilios",
      "ageRequirement": "18+",
      "additionalRequirements": "Llevar guantes y protector solar",
      "tasks": [
        "Recolectar basura",
        "Separar reciclables",
        "Asistir a voluntarios"
      ],
      "image": "base64string_or_filename.jpg"
    },

  ],
  "inscripciones": [
    {
      "id": "1",
      "eventoId": "1",
      "usuarioId": "2",
      "fecha_inscripcion": "2025-03-20"
    },
    {
      "id": "2",
      "eventoId": "1",
      "usuarioId": "3",
      "fecha_inscripcion": "2025-03-21"
    },
    {
      "id": "3",
      "eventoId": "2",
      "usuarioId": "2",
      "fecha_inscripcion": "2025-03-22"
    }
  ]
}